LICENSE.md
README.md
setup.py
bin/osm-export-tool
osm_export_tool/__init__.py
osm_export_tool/cmd.py
osm_export_tool/geometry.py
osm_export_tool/mapping.py
osm_export_tool/nontabular.py
osm_export_tool/package.py
osm_export_tool/sources.py
osm_export_tool/sql.py
osm_export_tool/tabular.py
osm_export_tool/mappings/HDX.yml
osm_export_tool/mappings/HDX_v2.yml
osm_export_tool/mappings/InAWARE.yml
osm_export_tool/mappings/default.yml
osm_export_tool/mappings/simple.yml
osm_export_tool_python.egg-info/PKG-INFO
osm_export_tool_python.egg-info/SOURCES.txt
osm_export_tool_python.egg-info/dependency_links.txt
osm_export_tool_python.egg-info/requires.txt
osm_export_tool_python.egg-info/top_level.txt
test/__init__.py
test/test_mapping.py
test/test_sources.py
test/test_sql.py