Metadata-Version: 2.1
Name: osm-export-tool-python
Version: 2.0.8
Summary: Convert OpenStreetMap data into GIS and mobile mapping file formats.
Home-page: https://github.com/hotosm/osm-export-tool-python
Author: Hot Tech Team
Author-email: sysadmin@hotosm.org
License: BSD-3-Clause
Platform: UNKNOWN
Classifier: Programming Language :: Python :: 3
Classifier: License :: OSI Approved :: BSD License
Classifier: Operating System :: OS Independent
License-File: LICENSE.md
